bazze_json_logger/__init__.py
bazze_json_logger/version.py
json_logger/__init__.py
bazze_json_logger-0.0.3.dist-info/METADATA
bazze_json_logger-0.0.3.dist-info/WHEEL
bazze_json_logger-0.0.3.dist-info/top_level.txt
bazze_json_logger-0.0.3.dist-info/RECORD
